bomberpy/__init__.py
bomberpy/__main__.py
bomberpy/block.py
bomberpy/bomb.py
bomberpy/boosters.py
bomberpy/enemy.py
bomberpy/explosion.py
bomberpy/game.py
bomberpy/main.py
bomberpy/menu.py
bomberpy/player.py
bomberpy/utils.py
bomberpy/wall.py
bomberpy/images/block.png
bomberpy/images/bomb.png
bomberpy/images/bomberman.png
bomberpy/images/boosters.png
bomberpy/images/deathplayer.png
bomberpy/images/enemy.png
bomberpy/images/explosion.png
bomberpy/images/game_over.png
bomberpy/images/grass.png
bomberpy/images/icon.png
bomberpy/images/mainmenu.png
bomberpy/images/pause_buttons.png
bomberpy/images/player.png
bomberpy/images/victory.png
bomberpy/images/wall.png
bomberpy/images/white_bomb.png
bomberpy/sounds/explosion_sound.wav
bomberpy/sounds/ievan_polka.wav
bomberpy/sounds/samba_de_janeiro.wav
bomberpy-0.0.4.dist-info/LICENSE
bomberpy-0.0.4.dist-info/METADATA
bomberpy-0.0.4.dist-info/WHEEL
bomberpy-0.0.4.dist-info/entry_points.txt
bomberpy-0.0.4.dist-info/top_level.txt
bomberpy-0.0.4.dist-info/RECORD
