Metadata-Version: 2.1
Name: bomberpy
Version: 0.0.4
Summary: O clássico Bomberman feito em python.
Home-page: https://github.com/vitorito/bomberpy
Author: João Victor O. Batista
Author-email: victorolivbati@gmail.com
License: MIT
Keywords: jogo,game,bomberman,arcade,ação
Platform: UNKNOWN
Requires-Python: >=3.6
Requires-Dist: pygame (>=2.0)
